{
    "asset": {
        "format": "png",
        "id": "48e99d52c05ad77259c4b701f1f618f6",
        "name": "570.png",
        "path": "file:C:/Users/20826/Documents/GitHub/learn_yolov1/dataset/image/570.png",
        "size": {
            "width": 720,
            "height": 720
        },
        "state": 2,
        "type": 1
    },
    "regions": [
        {
            "id": "BA12PmkZa",
            "type": "RECTANGLE",
            "tags": [
                "Aromatherapy"
            ],
            "boundingBox": {
                "height": 85.7680250783699,
                "width": 59.81191222570532,
                "left": 133.44827586206895,
                "top": 388.77742946708463
            },
            "points": [
                {
                    "x": 133.44827586206895,
                    "y": 388.77742946708463
                },
                {
                    "x": 193.26018808777428,
                    "y": 388.77742946708463
                },
                {
                    "x": 193.26018808777428,
                    "y": 474.5454545454545
                },
                {
                    "x": 133.44827586206895,
                    "y": 474.5454545454545
                }
            ]
        },
        {
            "id": "InnlqFeNf",
            "type": "RECTANGLE",
            "tags": [
                "book"
            ],
            "boundingBox": {
                "height": 174.92163009404388,
                "width": 197.49216300940438,
                "left": 492.3197492163009,
                "top": 429.9686520376175
            },
            "points": [
                {
                    "x": 492.3197492163009,
                    "y": 429.9686520376175
                },
                {
                    "x": 689.8119122257052,
                    "y": 429.9686520376175
                },
                {
                    "x": 689.8119122257052,
                    "y": 604.8902821316614
                },
                {
                    "x": 492.3197492163009,
                    "y": 604.8902821316614
                }
            ]
        },
        {
            "id": "DJOJvj4Fc",
            "type": "RECTANGLE",
            "tags": [
                "mouse"
            ],
            "boundingBox": {
                "height": 82.38244514106583,
                "width": 78.43260188087774,
                "left": 421.2225705329153,
                "top": 498.24451410658304
            },
            "points": [
                {
                    "x": 421.2225705329153,
                    "y": 498.24451410658304
                },
                {
                    "x": 499.6551724137931,
                    "y": 498.24451410658304
                },
                {
                    "x": 499.6551724137931,
                    "y": 580.6269592476489
                },
                {
                    "x": 421.2225705329153,
                    "y": 580.6269592476489
                }
            ]
        },
        {
            "id": "DltrjY33O",
            "type": "RECTANGLE",
            "tags": [
                "keyboard"
            ],
            "boundingBox": {
                "height": 130.9090909090909,
                "width": 295.67398119122254,
                "left": 119.90595611285265,
                "top": 484.70219435736675
            },
            "points": [
                {
                    "x": 119.90595611285265,
                    "y": 484.70219435736675
                },
                {
                    "x": 415.5799373040752,
                    "y": 484.70219435736675
                },
                {
                    "x": 415.5799373040752,
                    "y": 615.6112852664576
                },
                {
                    "x": 119.90595611285265,
                    "y": 615.6112852664576
                }
            ]
        },
        {
            "id": "cLsn9atYz",
            "type": "RECTANGLE",
            "tags": [
                "counter"
            ],
            "boundingBox": {
                "height": 110.59561128526644,
                "width": 168.71473354231972,
                "left": 306.1128526645768,
                "top": 577.2413793103448
            },
            "points": [
                {
                    "x": 306.1128526645768,
                    "y": 577.2413793103448
                },
                {
                    "x": 474.8275862068965,
                    "y": 577.2413793103448
                },
                {
                    "x": 474.8275862068965,
                    "y": 687.8369905956113
                },
                {
                    "x": 306.1128526645768,
                    "y": 687.8369905956113
                }
            ]
        },
        {
            "id": "P7EiBXpHA",
            "type": "RECTANGLE",
            "tags": [
                "cup"
            ],
            "boundingBox": {
                "height": 107.21003134796237,
                "width": 106.64576802507835,
                "left": 365.3605015673981,
                "top": 398.3699059561128
            },
            "points": [
                {
                    "x": 365.3605015673981,
                    "y": 398.3699059561128
                },
                {
                    "x": 472.00626959247643,
                    "y": 398.3699059561128
                },
                {
                    "x": 472.00626959247643,
                    "y": 505.5799373040752
                },
                {
                    "x": 365.3605015673981,
                    "y": 505.5799373040752
                }
            ]
        },
        {
            "id": "dk3293YgQ",
            "type": "RECTANGLE",
            "tags": [
                "lamp_switch"
            ],
            "boundingBox": {
                "height": 77.3040752351097,
                "width": 69.40438871473354,
                "left": 254.20062695924761,
                "top": 631.4106583072099
            },
            "points": [
                {
                    "x": 254.20062695924761,
                    "y": 631.4106583072099
                },
                {
                    "x": 323.60501567398114,
                    "y": 631.4106583072099
                },
                {
                    "x": 323.60501567398114,
                    "y": 708.7147335423197
                },
                {
                    "x": 254.20062695924761,
                    "y": 708.7147335423197
                }
            ]
        },
        {
            "id": "ew2mJCVw0",
            "type": "RECTANGLE",
            "tags": [
                "remote_control"
            ],
            "boundingBox": {
                "height": 99.31034482758619,
                "width": 125.26645768025077,
                "left": 36.95924764890282,
                "top": 620.6896551724137
            },
            "points": [
                {
                    "x": 36.95924764890282,
                    "y": 620.6896551724137
                },
                {
                    "x": 162.22570532915358,
                    "y": 620.6896551724137
                },
                {
                    "x": 162.22570532915358,
                    "y": 719.9999999999999
                },
                {
                    "x": 36.95924764890282,
                    "y": 719.9999999999999
                }
            ]
        }
    ],
    "version": "2.2.0"
}