{
    "asset": {
        "format": "png",
        "id": "589b04ed8d7d386152ab726522edde62",
        "name": "510.png",
        "path": "file:C:/Users/20826/Documents/GitHub/learn_yolov1/dataset/image/510.png",
        "size": {
            "width": 720,
            "height": 720
        },
        "state": 2,
        "type": 1
    },
    "regions": [
        {
            "id": "eMvec0YhK",
            "type": "RECTANGLE",
            "tags": [
                "book"
            ],
            "boundingBox": {
                "height": 172.10031347962382,
                "width": 180.564263322884,
                "left": 64.04388714733541,
                "top": 204.82758620689654
            },
            "points": [
                {
                    "x": 64.04388714733541,
                    "y": 204.82758620689654
                },
                {
                    "x": 244.6081504702194,
                    "y": 204.82758620689654
                },
                {
                    "x": 244.6081504702194,
                    "y": 376.92789968652033
                },
                {
                    "x": 64.04388714733541,
                    "y": 376.92789968652033
                }
            ]
        },
        {
            "id": "zTnc2fmZw",
            "type": "RECTANGLE",
            "tags": [
                "mouse"
            ],
            "boundingBox": {
                "height": 79.56112852664576,
                "width": 67.9937304075235,
                "left": 0,
                "top": 303.5736677115987
            },
            "points": [
                {
                    "x": 0,
                    "y": 303.5736677115987
                },
                {
                    "x": 67.9937304075235,
                    "y": 303.5736677115987
                },
                {
                    "x": 67.9937304075235,
                    "y": 383.13479623824446
                },
                {
                    "x": 0,
                    "y": 383.13479623824446
                }
            ]
        },
        {
            "id": "_vCMTpuF_",
            "type": "RECTANGLE",
            "tags": [
                "counter"
            ],
            "boundingBox": {
                "height": 78.43260188087774,
                "width": 49.373040752351095,
                "left": 0,
                "top": 404.0125391849529
            },
            "points": [
                {
                    "x": 0,
                    "y": 404.0125391849529
                },
                {
                    "x": 49.373040752351095,
                    "y": 404.0125391849529
                },
                {
                    "x": 49.373040752351095,
                    "y": 482.4451410658307
                },
                {
                    "x": 0,
                    "y": 482.4451410658307
                }
            ]
        }
    ],
    "version": "2.2.0"
}