{
    "asset": {
        "format": "png",
        "id": "b247bce20cb7e4577e223f7b4f9766c6",
        "name": "540.png",
        "path": "file:C:/Users/20826/Documents/GitHub/learn_yolov1/dataset/image/540.png",
        "size": {
            "width": 720,
            "height": 720
        },
        "state": 2,
        "type": 1
    },
    "regions": [
        {
            "id": "Q4Z7ZZ-9F",
            "type": "RECTANGLE",
            "tags": [
                "Spen"
            ],
            "boundingBox": {
                "height": 50.78369905956112,
                "width": 75.32915360501566,
                "left": 0,
                "top": 652.8526645768025
            },
            "points": [
                {
                    "x": 0,
                    "y": 652.8526645768025
                },
                {
                    "x": 75.32915360501566,
                    "y": 652.8526645768025
                },
                {
                    "x": 75.32915360501566,
                    "y": 703.6363636363636
                },
                {
                    "x": 0,
                    "y": 703.6363636363636
                }
            ]
        },
        {
            "id": "JiSPZnc5N",
            "type": "RECTANGLE",
            "tags": [
                "counter"
            ],
            "boundingBox": {
                "height": 91.97492163009403,
                "width": 166.45768025078368,
                "left": 153.1974921630094,
                "top": 499.9373040752351
            },
            "points": [
                {
                    "x": 153.1974921630094,
                    "y": 499.9373040752351
                },
                {
                    "x": 319.6551724137931,
                    "y": 499.9373040752351
                },
                {
                    "x": 319.6551724137931,
                    "y": 591.9122257053291
                },
                {
                    "x": 153.1974921630094,
                    "y": 591.9122257053291
                }
            ]
        },
        {
            "id": "hwmdwtuQS",
            "type": "RECTANGLE",
            "tags": [
                "lamp_switch"
            ],
            "boundingBox": {
                "height": 64.89028213166144,
                "width": 69.40438871473354,
                "left": 106.36363636363636,
                "top": 563.6990595611285
            },
            "points": [
                {
                    "x": 106.36363636363636,
                    "y": 563.6990595611285
                },
                {
                    "x": 175.7680250783699,
                    "y": 563.6990595611285
                },
                {
                    "x": 175.7680250783699,
                    "y": 628.58934169279
                },
                {
                    "x": 106.36363636363636,
                    "y": 628.58934169279
                }
            ]
        },
        {
            "id": "Q_-BeIpwY",
            "type": "RECTANGLE",
            "tags": [
                "mouse"
            ],
            "boundingBox": {
                "height": 80.12539184952978,
                "width": 84.63949843260187,
                "left": 268.30721003134795,
                "top": 411.9122257053291
            },
            "points": [
                {
                    "x": 268.30721003134795,
                    "y": 411.9122257053291
                },
                {
                    "x": 352.9467084639498,
                    "y": 411.9122257053291
                },
                {
                    "x": 352.9467084639498,
                    "y": 492.0376175548589
                },
                {
                    "x": 268.30721003134795,
                    "y": 492.0376175548589
                }
            ]
        },
        {
            "id": "LiBDieL9e",
            "type": "RECTANGLE",
            "tags": [
                "book"
            ],
            "boundingBox": {
                "height": 165.32915360501565,
                "width": 156.86520376175548,
                "left": 350.6896551724138,
                "top": 330.6583072100313
            },
            "points": [
                {
                    "x": 350.6896551724138,
                    "y": 330.6583072100313
                },
                {
                    "x": 507.5548589341692,
                    "y": 330.6583072100313
                },
                {
                    "x": 507.5548589341692,
                    "y": 495.987460815047
                },
                {
                    "x": 350.6896551724138,
                    "y": 495.987460815047
                }
            ]
        },
        {
            "id": "9GfunwfLj",
            "type": "RECTANGLE",
            "tags": [
                "cup"
            ],
            "boundingBox": {
                "height": 101.00313479623823,
                "width": 101.56739811912225,
                "left": 206.23824451410655,
                "top": 322.7586206896551
            },
            "points": [
                {
                    "x": 206.23824451410655,
                    "y": 322.7586206896551
                },
                {
                    "x": 307.8056426332288,
                    "y": 322.7586206896551
                },
                {
                    "x": 307.8056426332288,
                    "y": 423.7617554858934
                },
                {
                    "x": 206.23824451410655,
                    "y": 423.7617554858934
                }
            ]
        },
        {
            "id": "-54FoZzMk",
            "type": "RECTANGLE",
            "tags": [
                "keyboard"
            ],
            "boundingBox": {
                "height": 142.19435736677116,
                "width": 264.9216300940438,
                "left": 0,
                "top": 405.70532915360496
            },
            "points": [
                {
                    "x": 0,
                    "y": 405.70532915360496
                },
                {
                    "x": 264.9216300940438,
                    "y": 405.70532915360496
                },
                {
                    "x": 264.9216300940438,
                    "y": 547.8996865203761
                },
                {
                    "x": 0,
                    "y": 547.8996865203761
                }
            ]
        },
        {
            "id": "yFhz40qZX",
            "type": "RECTANGLE",
            "tags": [
                "Aromatherapy"
            ],
            "boundingBox": {
                "height": 80.68965517241378,
                "width": 23.416927899686517,
                "left": 0,
                "top": 337.42946708463944
            },
            "points": [
                {
                    "x": 0,
                    "y": 337.42946708463944
                },
                {
                    "x": 23.416927899686517,
                    "y": 337.42946708463944
                },
                {
                    "x": 23.416927899686517,
                    "y": 418.1191222570533
                },
                {
                    "x": 0,
                    "y": 418.1191222570533
                }
            ]
        }
    ],
    "version": "2.2.0"
}